tui_map_generator/__init__.py
tui_map_generator/__main__.py
tui_map_generator/diamond_square.py
tui_map_generator/maps/legend.xp
tui_map_generator-0.1.8.dist-info/LICENSE
tui_map_generator-0.1.8.dist-info/METADATA
tui_map_generator-0.1.8.dist-info/WHEEL
tui_map_generator-0.1.8.dist-info/entry_points.txt
tui_map_generator-0.1.8.dist-info/RECORD
