Metadata-Version: 2.1
Name: tui-map-generator
Version: 0.1.8
Summary: Height map generator using diamond square with TUI interface
Home-page: https://github.com/HubertReX/tui-map-generator
License: GPL-3.0-only
Author: Hubert Nafalski
Author-email: HubertReX@users.noreply.github.com
Requires-Python: >=3.9,<3.13
Classifier: License :: OSI Approved :: GNU General Public License v3 (GPLv3)
Classifier: Programming Language :: Python :: 3
Classifier: Programming Language :: Python :: 3.9
Classifier: Programming Language :: Python :: 3.10
Classifier: Programming Language :: Python :: 3.11
Requires-Dist: numpy (>=1.26.0,<2.0.0)
Requires-Dist: pyrexpaint (>=0.0.2,<0.0.3)
Requires-Dist: rich (>=13.6.0,<14.0.0)
Requires-Dist: rich-pixels (>=2.1.1,<3.0.0)
Requires-Dist: trogon (>=0.5.0,<0.6.0)
Project-URL: Repository, https://github.com/HubertReX/tui-map-generator
